madlib/__init__.py
madlib/data/dictionary.json.gz
madlib/data/sentences.json.gz
madlib_generator-0.1.1.dist-info/LICENSE
madlib_generator-0.1.1.dist-info/METADATA
madlib_generator-0.1.1.dist-info/WHEEL
madlib_generator-0.1.1.dist-info/top_level.txt
madlib_generator-0.1.1.dist-info/RECORD
