Metadata-Version: 2.1
Name: madlib_generator
Version: 0.1.1
Summary: A small example package
Home-page: https://github.com/Adrian-at-CrimsonAuzre/madlib_generator
Author: Adrian-at-CrimsonAuzre
Author-email: adrian@crimsonazure.com
License: UNKNOWN
Platform: UNKNOWN
Classifier: Programming Language :: Python :: 3
Classifier: License :: OSI Approved :: MIT License
Classifier: Operating System :: OS Independent
Requires-Python: >=3.6
License-File: LICENSE
